<?xml version="1.0" encoding="UTF-8"?>
<objects serializationModel="Studio.02.02.00">
	<object class="AudioFile" id="{1e2f33b5-25db-42e5-b123-8d7d175040e8}">
		<property name="assetPath">
			<value>Player_gets_hit_stereo_03.wav</value>
		</property>
		<property name="frequencyInKHz">
			<value>44.0999985</value>
		</property>
		<property name="channelCount">
			<value>2</value>
		</property>
		<property name="length">
			<value>1.1158503401360544</value>
		</property>
		<relationship name="masterAssetFolder">
			<destination>{7a61ddd5-1576-4eef-9d32-360ab9c87af4}</destination>
		</relationship>
	</object>
</objects>
